gls/__init__.py
gls-1.0.0.dist-info/METADATA
gls-1.0.0.dist-info/WHEEL
gls-1.0.0.dist-info/top_level.txt
gls-1.0.0.dist-info/RECORD
