Metadata-Version: 2.1
Name: gls
Version: 1.0.0
Summary: Gaussian Likelihood scoring method.
Home-page: UNKNOWN
Author: Maixent Chenebaux
Author-email: max.chbx@gmail.com
License: UNKNOWN
Platform: UNKNOWN
Classifier: Programming Language :: Python :: 3.7
Classifier: Operating System :: OS Independent
